private val
private final val
final val x = e

class PrivateVal {
  private val privateVal = 0
  def testPrivateVal = privateVal
  private final val privateFinalVal = 1
  def testPrivateFinalVal = privateFinalVal
}

javap -c
Compiled from "PrivateVal.scala"
public class PrivateVal {
  public int testPrivateVal();
    Code:
       0: aload_0       
       1: invokespecial #19                 // Method privateVal:()I
       4: ireturn       

  public int testPrivateFinalVal();
    Code:
       0: iconst_1      
       1: ireturn       

  public PrivateVal();
    Code:
       0: aload_0       
       1: invokespecial #24                 // Method java/lang/Object."<init>":()V
       4: aload_0       
       5: iconst_0      
       6: putfield      #14                 // Field privateVal:I
       9: return
}

private val
private final val
private val
private final val
