trait Speaks {
  def speak() = {
    println("woof")
  }
}

class Dog extends Speaks {
  def wag() = {
    println("wag wag")
  }
}

public void speak();
    flags: ACC_PUBLIC
    Code:
      stack=1, locals=1, args_size=1
         0: aload_0       
         1: invokestatic  #11                 // Method Speaks$class.speak:(LSpeaks;)V
         4: return        
      LineNumberTable:
        line 7: 0

public void wag();
    flags: ACC_PUBLIC
    Code:
      stack=2, locals=1, args_size=1
         0: getstatic     #18                 // Field scala/Predef$.MODULE$:Lscala/Predef$;
         3: ldc           #20                 // String wag wag
         5: invokevirtual #24                 // Method scala/Predef$.println:(Ljava/lang/Object;)V
         8: return        
      LineNumberTable:
        line 9: 0

public void speak();
  flags: ACC_PUBLIC, ACC_BRIDGE
  Code:
    stack=1, locals=1, args_size=1
       0: aload_0       
       1: invokestatic  #11                 // Method Speaks$class.speak:(LSpeaks;)V
       4: return        
    LineNumberTable:
      line 7: 0

public void wag();
  flags: ACC_PUBLIC
  Code:
    stack=2, locals=1, args_size=1
       0: getstatic     #18                 // Field scala/Predef$.MODULE$:Lscala/Predef$;
       3: ldc           #20                 // String wag wag
       5: invokevirtual #24                 // Method scala/Predef$.println:(Ljava/lang/Object;)V
       8: return        
    LineNumberTable:
      line 9: 0

