public class Common 
{
  public Common(List list)
  {
    ...  
  }  
}

List
Collection
public class Common 
{
  public Common(Collection collection)
  {
    ...
  }
}

NoSuchMethodError
Compiled from "Client.java"
public class Client extends java.lang.Object{
public Client();
  Code:
   0:   aload_0
   1:   invokespecial   #1; //Method java/lang/Object."<init>":()V
   4:   return

public static void main(java.lang.String[]);
  Code:
   0:   new #2; //class ArrayList
   3:   dup
   4:   invokespecial   #3; //Method java/util/ArrayList."<init>":()V
   7:   astore_1
   8:   new #4; //class Common
   11:  dup
   12:  aload_1
   13:  invokespecial   #5; //Method Common."<init>":(Ljava/util/List;)V
   16:  pop
   17:  return

}

